LanguageToolBear-0.9.0.1482008498.dist-info/DESCRIPTION.rst
LanguageToolBear-0.9.0.1482008498.dist-info/METADATA
LanguageToolBear-0.9.0.1482008498.dist-info/RECORD
LanguageToolBear-0.9.0.1482008498.dist-info/WHEEL
LanguageToolBear-0.9.0.1482008498.dist-info/entry_points.txt
LanguageToolBear-0.9.0.1482008498.dist-info/metadata.json
LanguageToolBear-0.9.0.1482008498.dist-info/top_level.txt
coalaLanguageToolBear/LanguageToolBear.py
coalaLanguageToolBear/__init__.py
